{
  "kind": "collectionType",
  "collectionName": "restaurants",
  "info": {
    "singularName": "restaurant",
    "pluralName": "restaurants",
    "displayName": "Restaurants"
  },
  "options": {
    "draftAndPublish": true
  },
  "pluginOptions": {},
  "attributes": {
    "description": {
      "type": "text"
    },
    "title": {
      "type": "string"
    },
    "image": {
      "allowedTypes": [
        "images",
        "files",
        "videos",
        "audios"
      ],
      "type": "media",
      "multiple": false
    },
    "dishes": {
      "type": "relation",
      "relation": "oneToMany",
      "target": "api::dish.dish",
      "mappedBy": "restaurant"
    }
  }
}
